peinan_utils/VERSION
peinan_utils/__init__.py
peinan_utils/fonts/NotoSansCJKjp-Black.otf
peinan_utils/fonts/NotoSansCJKjp-Bold.otf
peinan_utils/fonts/NotoSansCJKjp-Light.otf
peinan_utils/fonts/NotoSansCJKjp-Medium.otf
peinan_utils/fonts/NotoSansCJKjp-Regular.otf
peinan_utils/fonts/NotoSansCJKjp-Thin.otf
peinan_utils/logger.py
peinan_utils/matplotlib_utils.py
peinan_utils/parser.py
peinan_utils/stat_utils.py
peinan_utils/vectorizer.py
peinan_utils-0.1.1.dist-info/LICENSE
peinan_utils-0.1.1.dist-info/WHEEL
peinan_utils-0.1.1.dist-info/METADATA
peinan_utils-0.1.1.dist-info/RECORD
