Metadata-Version: 2.1
Name: peinan-utils
Version: 0.1.1
Summary: An util package for myself. (Mostly about NLP)
Home-page: https://github.com/peinan/peinan-utils-py
License: MIT
Keywords: utils,nlp,tools
Author: Peinan ZHANG
Author-email: peinan7@gmail.com
Requires-Python: >=3.8,<4.0
Classifier: Development Status :: 3 - Alpha
Classifier: License :: OSI Approved :: MIT License
Classifier: Programming Language :: Python :: 3
Classifier: Programming Language :: Python :: 3.7
Classifier: Programming Language :: Python :: 3.8
Classifier: Programming Language :: Python :: 3.9
Classifier: Topic :: Utilities
Requires-Dist: ipadic (>=1.0.0,<2.0.0)
Requires-Dist: loguru (>=0.5.3,<0.6.0)
Requires-Dist: matplotlib (>=3.4.2,<4.0.0)
Requires-Dist: mecab-python3 (>=1.0.4,<2.0.0)
Project-URL: Repository, https://github.com/peinan/peinan-utils-py
